{
  "original_content": "# Assignment: My Digital Environment (PowerPoint)\n\nCreate a PowerPoint presentation on the topic \"My Digital Environment\". The presentation must meet the following requirements:\n\n## Technical Structure\n* **Slide count:** 4–10 slides.\n* **Layout:** Use at least two different slide layouts.\n* **Footer:** Include page number, author's name and automatically updating date.\n\n## Content Requirements\n* **Equipment:** Describe what technical devices you use daily.\n* **Social media:** Tell what social media services you use.\n* **Links:** Include at least one link to external websites.\n* **Media:** Add a video related to the topic and at least one image.\n* **Visualization:** Include one **SmartArt diagram**.\n\n## Formatting and Presentation Style\n* **Fonts:** Use font formatting in at least two different ways (e.g. bolding, italicizing or changing font).\n* **Notes:** Add tips for presenting the slides to the notes section of at least one slide.",
  "keywords": [
    {
      "term": "requirements",
      "frequency": 2,
      "relevance": 0.2,
      "category": "business_term",
      "tags": [
        "auto_extraction",
        "business_documentation"
      ],
      "source_file": "/common/active/sblo/Dev/FinCom/docs/english_business_forms/Minun digitaalinen ympäristöni .md",
      "position_in_text": 164,
      "related_keywords": []
    },
    {
      "term": "form",
      "frequency": 2,
      "relevance": 0.2,
      "category": "business_term",
      "tags": [
        "auto_extraction",
        "business_documentation"
      ],
      "source_file": "/common/active/sblo/Dev/FinCom/docs/english_business_forms/Minun digitaalinen ympäristöni .md",
      "position_in_text": 712,
      "related_keywords": []
    },
    {
      "term": "service",
      "frequency": 1,
      "relevance": 0.1,
      "category": "business_term",
      "tags": [
        "auto_extraction",
        "business_documentation"
      ],
      "source_file": "/common/active/sblo/Dev/FinCom/docs/english_business_forms/Minun digitaalinen ympäristöni .md",
      "position_in_text": 504,
      "related_keywords": []
    },
    {
      "term": "services",
      "frequency": 1,
      "relevance": 0.1,
      "category": "business_term",
      "tags": [
        "auto_extraction",
        "business_documentation"
      ],
      "source_file": "/common/active/sblo/Dev/FinCom/docs/english_business_forms/Minun digitaalinen ympäristöni .md",
      "position_in_text": 504,
      "related_keywords": []
    },
    {
      "term": "digital",
      "frequency": 2,
      "relevance": 0.2,
      "category": "business_term",
      "tags": [
        "auto_extraction",
        "business_documentation"
      ],
      "source_file": "/common/active/sblo/Dev/FinCom/docs/english_business_forms/Minun digitaalinen ympäristöni .md",
      "position_in_text": 17,
      "related_keywords": []
    },
    {
      "term": "Minun digitaalinen ympäristöni ",
      "frequency": 3,
      "relevance": 0.9,
      "category": "document_specific",
      "tags": [
        "file_name_based",
        "auto_extraction"
      ],
      "source_file": "/common/active/sblo/Dev/FinCom/docs/english_business_forms/Minun digitaalinen ympäristöni .md",
      "position_in_text": 0,
      "related_keywords": []
    }
  ],
  "ecs_elements": {
    "source_file": "/common/active/sblo/Dev/FinCom/docs/english_business_forms/Minun digitaalinen ympäristöni .md",
    "extraction_date": "2026-02-09T23:01:32.659559",
    "entities": [
      {
        "name": "Business Entity",
        "description": "Generic business entity mentioned in the document",
        "attributes": {
          "type": "varies_by_document",
          "requirements": "depends_on_document_context",
          "processes": "mentioned_in_document"
        },
        "tags": [
          "business_entity",
          "document_context"
        ],
        "source_file": "/common/active/sblo/Dev/FinCom/docs/english_business_forms/Minun digitaalinen ympäristöni .md",
        "relationships": {}
      }
    ],
    "components": [
      {
        "name": "Document Requirements",
        "description": "Requirements specified in the document",
        "properties": {
          "specified_in": "/common/active/sblo/Dev/FinCom/docs/english_business_forms/Minun digitaalinen ympäristöni .md",
          "type": "business_requirements",
          "complexity": "medium"
        },
        "data_schema": {},
        "tags": [
          "requirements",
          "business_rules"
        ],
        "source_file": "/common/active/sblo/Dev/FinCom/docs/english_business_forms/Minun digitaalinen ympäristöni .md"
      }
    ],
    "systems": [
      {
        "name": "Document Process System",
        "description": "Process system described in the document",
        "behavior": "Defined by document content",
        "dependencies": [],
        "triggers": [
          "document_review"
        ],
        "tags": [
          "process",
          "system"
        ],
        "source_file": "/common/active/sblo/Dev/FinCom/docs/english_business_forms/Minun digitaalinen ympäristöni .md"
      }
    ]
  },
  "constraints": [
    {
      "id": "constraint_Minun_digitaalinen_ympäristöni__review",
      "title": "Minun digitaalinen ympäristöni .md Review Required",
      "description": "Document Minun digitaalinen ympäristöni .md needs to be reviewed for compliance",
      "constraint_type": "procedural",
      "condition": "document_reviewed == True",
      "scope": "document_compliance",
      "severity": "info",
      "source_file": "/common/active/sblo/Dev/FinCom/docs/english_business_forms/Minun digitaalinen ympäristöni .md",
      "tags": [
        "compliance",
        "review"
      ],
      "related_constraints": [],
      "validation_logic": "check_document_review_status(document_id)",
      "error_message": "Document Minun digitaalinen ympäristöni .md requires review"
    }
  ],
  "metadata": {
    "source_file": "/common/active/sblo/Dev/FinCom/docs/english_business_forms/Minun digitaalinen ympäristöni .md",
    "title": "Minun digitaalinen ympäristöni ",
    "description": "Documentation file: Minun digitaalinen ympäristöni .md",
    "tags": [
      "documentation",
      "business",
      "finland"
    ],
    "categories": [
      "business_documentation"
    ],
    "related_files": [],
    "creation_date": "2026-02-09T23:01:32.659566",
    "last_modified": "2026-02-09T23:01:32.659567",
    "author": "auto_processing",
    "version": "1.0",
    "relevance_score": 0.7,
    "content_type": "documentation",
    "business_domains": [
      "business_operations"
    ],
    "difficulty_level": "intermediate",
    "estimated_reading_time": 1,
    "word_count": 142,
    "language": "en",
    "keywords": [
      "requirements",
      "form",
      "service",
      "services",
      "digital",
      "Minun digitaalinen ympäristöni "
    ],
    "related_entities": [
      "Business Entity"
    ],
    "related_components": [
      "Document Requirements"
    ],
    "related_systems": [
      "Document Process System"
    ],
    "related_constraints": [
      "constraint_Minun_digitaalinen_ympäristöni__review"
    ],
    "custom_fields": {
      "document_type": "business_form",
      "processing_status": "completed",
      "original_file_name": "Minun digitaalinen ympäristöni .md"
    }
  },
  "processing_date": "2026-02-09T23:01:32.659590",
  "processor": "systematic_batch_processor"
}